pycdlib/__init__.py
pycdlib/backport_functools.py
pycdlib/dates.py
pycdlib/dr.py
pycdlib/eltorito.py
pycdlib/facade.py
pycdlib/headervd.py
pycdlib/inode.py
pycdlib/isohybrid.py
pycdlib/path_table_record.py
pycdlib/py.typed
pycdlib/pycdlib.py
pycdlib/pycdlibexception.py
pycdlib/pycdlibio.py
pycdlib/rockridge.py
pycdlib/udf.py
pycdlib/utils.py
pycdlib-1.13.0.data/data/share/man/man1/pycdlib-explorer.1
pycdlib-1.13.0.data/data/share/man/man1/pycdlib-extract-files.1
pycdlib-1.13.0.data/data/share/man/man1/pycdlib-genisoimage.1
pycdlib-1.13.0.data/scripts/pycdlib-explorer
pycdlib-1.13.0.data/scripts/pycdlib-extract-files
pycdlib-1.13.0.data/scripts/pycdlib-genisoimage
pycdlib-1.13.0.dist-info/COPYING
pycdlib-1.13.0.dist-info/METADATA
pycdlib-1.13.0.dist-info/WHEEL
pycdlib-1.13.0.dist-info/top_level.txt
pycdlib-1.13.0.dist-info/RECORD
