Metadata-Version: 2.1
Name: pycdlib
Version: 1.13.0
Summary: Pure python ISO manipulation library
Home-page: http://github.com/clalancette/pycdlib
Author: Chris Lalancette
Author-email: clalancette@gmail.com
License: LGPLv2
Keywords: iso9660 iso ecma119 rockridge joliet eltorito udf
Platform: UNKNOWN
Classifier: Development Status :: 5 - Production/Stable
Classifier: Intended Audience :: Developers
Classifier: License :: OSI Approved :: GNU Lesser General Public License v2 (LGPLv2)
Classifier: Natural Language :: English
Classifier: Programming Language :: Python :: 2.7
Classifier: Programming Language :: Python :: 3.4
License-File: COPYING
